mulact/__init__.py
mulact/config.py
mulact/data/__init__.py
mulact/data/pre_processing.py
mulact/utils/__init__.py
mulact-0.1.0.dist-info/METADATA
mulact-0.1.0.dist-info/WHEEL
mulact-0.1.0.dist-info/top_level.txt
mulact-0.1.0.dist-info/RECORD
