Metadata-Version: 2.4
Name: mulact
Version: 0.1.0
Summary: Add your description here
Requires-Python: >=3.12
Requires-Dist: pandas>=2.3.0
Requires-Dist: pyomo>=6.9.2
Provides-Extra: notebook
Requires-Dist: ipykernel>=6.29.5; extra == "notebook"
